<annotation>
	<folder>data</folder>
	<filename>v2-3838c125c62989bc253f35426d181bdf_b.jpg</filename>
	<path>E:\Python\Here_is_a_Loopy\data\v2-3838c125c62989bc253f35426d181bdf_b.jpg</path>
	<source>
		<database>Unknown</database>
	</source>
	<size>
		<width>720</width>
		<height>1555</height>
		<depth>3</depth>
	</size>
	<segmented>0</segmented>
	<object>
		<name>white</name>
		<pose>Unspecified</pose>
		<truncated>0</truncated>
		<difficult>0</difficult>
		<bndbox>
			<xmin>160</xmin>
			<ymin>515</ymin>
			<xmax>466</xmax>
			<ymax>727</ymax>
		</bndbox>
	</object>
	<object>
		<name>yellow</name>
		<pose>Unspecified</pose>
		<truncated>0</truncated>
		<difficult>0</difficult>
		<bndbox>
			<xmin>408</xmin>
			<ymin>886</ymin>
			<xmax>646</xmax>
			<ymax>1187</ymax>
		</bndbox>
	</object>
</annotation>
